thw_submission_generator/__init__.py
thw_submission_generator-0.1.1.dist-info/entry_points.txt
thw_submission_generator-0.1.1.dist-info/WHEEL
thw_submission_generator-0.1.1.dist-info/METADATA
thw_submission_generator-0.1.1.dist-info/RECORD
