Metadata-Version: 2.1
Name: thw-submission-generator
Version: 0.1.1
Summary: Generate map descriptions for hiveworkshop.com
License: MIT
Author: Cokemonkey11
Author-email: Cokemonkey11@gmail.com
Requires-Python: >=3.6,<4.0
Classifier: License :: OSI Approved :: MIT License
Classifier: Programming Language :: Python :: 3
Classifier: Programming Language :: Python :: 3.10
Classifier: Programming Language :: Python :: 3.6
Classifier: Programming Language :: Python :: 3.7
Classifier: Programming Language :: Python :: 3.8
Classifier: Programming Language :: Python :: 3.9
Requires-Dist: ruamel.yaml (>=0.17.20,<0.18.0)
